ApacheSparkShejiYuShixian/README.md
ApacheSparkShejiYuShixian/__init__.py
ApacheSparkShejiYuShixian/__main__.py
ApacheSparkShejiYuShixian/file.epub
ApacheSparkShejiYuShixian/index.html
ApacheSparkShejiYuShixian/css/__init__.py
ApacheSparkShejiYuShixian/css/annotations.css
ApacheSparkShejiYuShixian/css/main.css
ApacheSparkShejiYuShixian/css/normalize.css
ApacheSparkShejiYuShixian/css/popup.css
ApacheSparkShejiYuShixian/font/__init__.py
ApacheSparkShejiYuShixian/font/fontello.eot
ApacheSparkShejiYuShixian/font/fontello.svg
ApacheSparkShejiYuShixian/font/fontello.ttf
ApacheSparkShejiYuShixian/font/fontello.woff
ApacheSparkShejiYuShixian/img/__init__.py
ApacheSparkShejiYuShixian/img/annotator-glyph-sprite.png
ApacheSparkShejiYuShixian/img/annotator-icon-sprite.png
ApacheSparkShejiYuShixian/img/apple-touch-icon.png
ApacheSparkShejiYuShixian/img/cancelfullscreen.png
ApacheSparkShejiYuShixian/img/close.png
ApacheSparkShejiYuShixian/img/fullscreen.png
ApacheSparkShejiYuShixian/img/loader.gif
ApacheSparkShejiYuShixian/img/menu-icon.png
ApacheSparkShejiYuShixian/img/save.png
ApacheSparkShejiYuShixian/img/saved.png
ApacheSparkShejiYuShixian/img/settings-s.png
ApacheSparkShejiYuShixian/img/settings.png
ApacheSparkShejiYuShixian/img/star.png
ApacheSparkShejiYuShixian/js/__init__.py
ApacheSparkShejiYuShixian/js/epub.js
ApacheSparkShejiYuShixian/js/epub.min.js
ApacheSparkShejiYuShixian/js/epub.min.map
ApacheSparkShejiYuShixian/js/hooks.min.js
ApacheSparkShejiYuShixian/js/hooks.min.map
ApacheSparkShejiYuShixian/js/reader.js
ApacheSparkShejiYuShixian/js/reader.js.map
ApacheSparkShejiYuShixian/js/reader.min.js
ApacheSparkShejiYuShixian/js/reader.min.map
ApacheSparkShejiYuShixian/js/hooks/__init__.py
ApacheSparkShejiYuShixian/js/hooks/extensions/__init__.py
ApacheSparkShejiYuShixian/js/hooks/extensions/highlight.js
ApacheSparkShejiYuShixian/js/libs/__init__.py
ApacheSparkShejiYuShixian/js/libs/jquery.min.js
ApacheSparkShejiYuShixian/js/libs/localforage.min.js
apache_spark_sheji_yu_shixian-2024.2.29.0.dist-info/METADATA
apache_spark_sheji_yu_shixian-2024.2.29.0.dist-info/WHEEL
apache_spark_sheji_yu_shixian-2024.2.29.0.dist-info/entry_points.txt
apache_spark_sheji_yu_shixian-2024.2.29.0.dist-info/top_level.txt
apache_spark_sheji_yu_shixian-2024.2.29.0.dist-info/RECORD
